v8ball/__init__.py
v8ball/van/__init__.py
v8ball/van/answers.json
v8ball/van/eightball.py
vans_eightball-0.0.2.dist-info/LICENSE
vans_eightball-0.0.2.dist-info/METADATA
vans_eightball-0.0.2.dist-info/WHEEL
vans_eightball-0.0.2.dist-info/entry_points.txt
vans_eightball-0.0.2.dist-info/top_level.txt
vans_eightball-0.0.2.dist-info/RECORD
